README.rst
setup.py
Chronyk.egg-info/PKG-INFO
Chronyk.egg-info/SOURCES.txt
Chronyk.egg-info/dependency_links.txt
Chronyk.egg-info/top_level.txt
chronyk/__init__.py
chronyk/chronyk.py