Metadata-Version: 1.1
Name: Chronyk
Version: 1.0
Summary: A library for parsing human-written times and dates.
Home-page: https://github.com/KoffeinFlummi/Chronyk
Author: Felix "KoffeinFlummi" Wiegand
Author-email: koffeinflummi@gmail.com
License: MIT
Keywords: time date clock human parser timezone
Platform: UNKNOWN
Classifier: Development Status :: 4 - Beta
Classifier: Intended Audience :: Developers
Classifier: License :: OSI Approved :: MIT License
Classifier: Natural Language :: English
Classifier: Programming Language :: Python :: 3.2
Classifier: Programming Language :: Python :: 3.3
Classifier: Programming Language :: Python :: 3.4
